propgraph/__init__.py
propgraph/__main__.py
propgraph/cypher.py
propgraph/schema.py
propgraph/util.py
pypropgraph-0.6.0.dist-info/licenses/LICENSE
pypropgraph-0.6.0.dist-info/METADATA
pypropgraph-0.6.0.dist-info/WHEEL
pypropgraph-0.6.0.dist-info/top_level.txt
pypropgraph-0.6.0.dist-info/RECORD
