Metadata-Version: 2.4
Name: pypropgraph
Version: 0.6.0
Summary: A property graphs library for importing and generating cypher in python
Home-page: https://github.com/alexmilowski/pypropgraph
Author: Alex Miłowski
Author-email: alex@milowski.com
License: MIT License
Keywords: cypher,property,graph
License-File: LICENSE
Requires-Dist: pyyaml
Requires-Dist: lark-parser
Provides-Extra: redis
Requires-Dist: redis; extra == "redis"
Provides-Extra: falkordb
Requires-Dist: FalkorDB; extra == "falkordb"
Dynamic: license-file
